{
  "version": "0.14.0",
  "round": {
    "index": 122,
    "startedAt": 1627524223
  },
  "clientTotal": 8,
  "playerTotal": 7,
  "spectatorTotal": 1,
  "recentPlayersTotal": 10,
  "spritesTotal": 170,
  "leaderboard": [
    {
      "name": "Shadowdeath",
      "id": "e5pBMugJywXP63LuABgv",
      "avatar": 0,
      "network": "bsc",
      "address": "0xb8b525A87adC048282bd724171fF02eb43De41F5",
      "device": "desktop",
      "position": {
        "x": -8.26852305845806,
        "y": -12.245406267366295
      },
      "target": {
        "x": -9.84,
        "y": -10.92
      },
      "clientPosition": {
        "x": -8.17,
        "y": -12.25
      },
      "rotation": null,
      "xp": 94.67999999999998,
      "latency": 51,
      "kills": 5,
      "deaths": 0,
      "points": 820,
      "evolves": 109,
      "powerups": 820,
      "rewards": 4,
      "orbs": 0,
      "isMasterClient": false,
      "isDisconnected": false,
      "isDead": false,
      "isSpectating": false,
      "overrideSpeed": null,
      "overrideCameraSize": null,
      "cameraSize": 3,
      "speed": 3,
      "joinedAt": 1627524091,
      "hash": "Zt63rUfQ8",
      "lastReportedTime": "1627524402608",
      "lastUpdate": 1627524403,
      "gameMode": "Sprite Leader",
      "log": {
        "kills": [
          "AnlErvFSc",
          "ULX5edj2w",
          "fsWqxo1KU",
          "fsWqxo1KU",
          "ULX5edj2w"
        ],
        "deaths": [],
        "revenge": 0,
        "resetPosition": 0
      },
      "startedRoundAt": 1627524223
    },
    {
      "name": "fenears",
      "id": "-epZoAapqiRo7FGHABiC",
      "avatar": 0,
      "network": "bsc",
      "address": "0x63B6643276C704933B3Cf5AdB1677466B4BAe2f7",
      "device": "desktop",
      "position": {
        "x": -11.365951923250806,
        "y": -8.680619705719595
      },
      "target": {
        "x": -14.32,
        "y": -8.74
      },
      "clientPosition": {
        "x": -11.25,
        "y": -8.74
      },
      "rotation": null,
      "xp": 42.439999999999536,
      "latency": 216.5,
      "kills": 2,
      "deaths": 2,
      "points": 499,
      "evolves": 50,
      "powerups": 499,
      "rewards": 5,
      "orbs": 0,
      "isMasterClient": false,
      "isDisconnected": false,
      "isDead": false,
      "isSpectating": false,
      "overrideSpeed": null,
      "overrideCameraSize": null,
      "cameraSize": 3,
      "speed": 3,
      "joinedAt": 1627524392,
      "hash": "ULX5edj2w",
      "lastReportedTime": "1627524402277",
      "lastUpdate": 1627524403,
      "gameMode": "Sprite Leader",
      "log": {
        "kills": [
          "fsWqxo1KU",
          "vXWwUsxYw"
        ],
        "deaths": [
          "Zt63rUfQ8",
          "Zt63rUfQ8"
        ],
        "revenge": 0,
        "resetPosition": 0
      },
      "isInvincible": true
    },
    {
      "name": "OENNEAR",
      "id": "1iZCJINjM6gumtz6ABiD",
      "avatar": 0,
      "network": "bsc",
      "address": "0x4A7F54bFc2ef00983608B7aF1d88fFE2eC7fAf34",
      "device": "desktop",
      "position": {
        "x": -12.513871423283963,
        "y": -11.63709931089091
      },
      "target": {
        "x": -5.7,
        "y": -11.35
      },
      "clientPosition": {
        "x": -10.19,
        "y": -11.63
      },
      "rotation": null,
      "xp": 0,
      "latency": 213,
      "kills": 0,
      "deaths": 3,
      "points": 236,
      "evolves": 12,
      "powerups": 236,
      "rewards": 5,
      "orbs": 0,
      "isMasterClient": false,
      "isDisconnected": true,
      "isDead": true,
      "isSpectating": false,
      "overrideSpeed": null,
      "overrideCameraSize": null,
      "cameraSize": 3,
      "speed": 3,
      "joinedAt": null,
      "hash": "fsWqxo1KU",
      "lastReportedTime": "1627524397303",
      "lastUpdate": 1627524398,
      "gameMode": "Sprite Leader",
      "log": {
        "kills": [],
        "deaths": [
          "ULX5edj2w",
          "Zt63rUfQ8",
          "Zt63rUfQ8"
        ],
        "revenge": 0,
        "resetPosition": 0
      }
    },
    {
      "name": "coco",
      "id": "ykVfgSFpZD2kfDWNABiJ",
      "avatar": 0,
      "network": "bsc",
      "address": "0xaCF5F0CC710A0B913C2eB58E3d2d84F388ab0BDd",
      "device": "desktop",
      "position": {
        "x": -4.83,
        "y": -11.6
      },
      "target": {
        "x": -4.83,
        "y": -11.6
      },
      "clientPosition": {
        "x": -4.83,
        "y": -11.6
      },
      "rotation": null,
      "xp": 71.63999999999996,
      "latency": 237,
      "kills": 0,
      "deaths": 0,
      "points": 110,
      "evolves": 4,
      "powerups": 110,
      "rewards": 1,
      "orbs": 0,
      "isMasterClient": false,
      "isDisconnected": false,
      "isDead": false,
      "isSpectating": false,
      "overrideSpeed": null,
      "overrideCameraSize": null,
      "cameraSize": 3,
      "speed": 3,
      "joinedAt": 1627524402,
      "hash": "+jg8vQ3Y4",
      "lastReportedTime": "1627524402277",
      "lastUpdate": 1627524402,
      "gameMode": "Sprite Leader",
      "log": {
        "kills": [],
        "deaths": [],
        "revenge": 0,
        "resetPosition": 0
      }
    },
    {
      "name": "aepol",
      "id": "GWl9HBxITNK9dZijABh9",
      "avatar": 1,
      "network": "bsc",
      "address": "0xDcc850Ed895626561DaEdf6c6Dc9f8D29a67D94C",
      "device": "desktop",
      "position": {
        "x": -2.9765510836480362,
        "y": -6.946284525062619
      },
      "target": {
        "x": -3.79,
        "y": -7.74
      },
      "clientPosition": {
        "x": -3.09,
        "y": -7.04
      },
      "rotation": null,
      "xp": 9.3399999999999,
      "latency": 186,
      "kills": 0,
      "deaths": 1,
      "points": 80,
      "evolves": 2,
      "powerups": 80,
      "rewards": 2,
      "orbs": 0,
      "isMasterClient": false,
      "isDisconnected": false,
      "isDead": false,
      "isSpectating": false,
      "overrideSpeed": null,
      "overrideCameraSize": null,
      "cameraSize": 3,
      "speed": 2.55,
      "joinedAt": 1627524384,
      "hash": "vXWwUsxYw",
      "lastReportedTime": "1627524402358",
      "lastUpdate": 1627524402,
      "gameMode": "Sprite Leader",
      "log": {
        "kills": [],
        "deaths": [
          "ULX5edj2w"
        ],
        "revenge": 0,
        "resetPosition": 0
      }
    },
    {
      "name": "duolaameng",
      "id": "J3rO_AoSEmJcOFMQABiF",
      "avatar": 0,
      "network": "bsc",
      "address": "0x688d54E6aCB46731eaEaE475ACd5c0EB930E328a",
      "device": "mobile",
      "position": {
        "x": -1.2543558454058237,
        "y": -9.944457322555067
      },
      "target": {
        "x": -2.27,
        "y": -9.2
      },
      "clientPosition": {
        "x": -1.27,
        "y": -10.2
      },
      "rotation": null,
      "xp": 69.59999999999962,
      "latency": 267,
      "kills": 0,
      "deaths": 0,
      "points": 58,
      "evolves": 0,
      "powerups": 58,
      "rewards": 0,
      "orbs": 0,
      "isMasterClient": false,
      "isDisconnected": false,
      "isDead": false,
      "isSpectating": false,
      "overrideSpeed": null,
      "overrideCameraSize": null,
      "cameraSize": 3,
      "speed": 3,
      "joinedAt": 1627524396,
      "hash": "tiWE8nTX4",
      "lastReportedTime": "1627524402176",
      "lastUpdate": 1627524403,
      "gameMode": "Sprite Leader",
      "log": {
        "kills": [],
        "deaths": [],
        "revenge": 0,
        "resetPosition": 0
      }
    },
    {
      "name": "Giorno giovanna",
      "id": "iT_MljjkFpqAKSGZABhD",
      "avatar": 0,
      "network": "bsc",
      "address": "0xa68b6df97aa8164AF3e357757E60CbA4F8794C0D",
      "device": "desktop",
      "position": {
        "x": -0.39144337518542405,
        "y": -0.8082822008821559
      },
      "target": {
        "x": 8.51,
        "y": 4.46
      },
      "clientPosition": {
        "x": -0.44,
        "y": -0.87
      },
      "rotation": null,
      "xp": 0,
      "latency": 162,
      "kills": 0,
      "deaths": 1,
      "points": 21,
      "evolves": 1,
      "powerups": 21,
      "rewards": 0,
      "orbs": 0,
      "isMasterClient": false,
      "isDisconnected": true,
      "isDead": true,
      "isSpectating": false,
      "overrideSpeed": null,
      "overrideCameraSize": null,
      "cameraSize": 3,
      "speed": 3,
      "joinedAt": null,
      "hash": "AnlErvFSc",
      "lastReportedTime": "1627524234191",
      "lastUpdate": 1627524234,
      "gameMode": "Sprite Leader",
      "log": {
        "kills": [],
        "deaths": [
          "Zt63rUfQ8"
        ],
        "revenge": 0,
        "resetPosition": 0
      }
    },
    {
      "name": "onestwo",
      "id": "oiJ8A4-U7Cs0e4aGABhF",
      "avatar": 0,
      "network": "bsc",
      "address": "0x7e48CA4A094b40609De260Fc02a9C0749266BC56",
      "device": "desktop",
      "position": {
        "x": -7.697098010751481,
        "y": -12.314762477717547
      },
      "target": {
        "x": -9.46,
        "y": -11.8
      },
      "clientPosition": {
        "x": -7.61,
        "y": -12.34
      },
      "rotation": null,
      "xp": 0,
      "latency": 213.5,
      "kills": 0,
      "deaths": 0,
      "points": 8,
      "evolves": 0,
      "powerups": 8,
      "rewards": 0,
      "orbs": 0,
      "isMasterClient": false,
      "isDisconnected": true,
      "isDead": true,
      "isSpectating": false,
      "overrideSpeed": null,
      "overrideCameraSize": null,
      "cameraSize": 3,
      "speed": 3,
      "joinedAt": null,
      "hash": "B8QlqDKy4",
      "lastReportedTime": "1627524236088",
      "lastUpdate": 1627524236,
      "gameMode": "Sprite Leader",
      "log": {
        "kills": [],
        "deaths": [],
        "revenge": 0,
        "resetPosition": 0
      }
    },
    {
      "name": "Guest602",
      "id": "mNva0x0iATiVekuDABiH",
      "avatar": 0,
      "network": "bsc",
      "address": "0xc84ce216fef4EC8957bD0Fb966Bb3c3E2c938082",
      "device": "mobile",
      "position": {
        "x": -7.6101919811257535,
        "y": -13.414705190187053
      },
      "target": {
        "x": -7.69,
        "y": -13.14
      },
      "clientPosition": {
        "x": -7.42,
        "y": -13.23
      },
      "rotation": null,
      "xp": 14.51999999999985,
      "latency": 328,
      "kills": 0,
      "deaths": 0,
      "points": 2,
      "evolves": 0,
      "powerups": 2,
      "rewards": 0,
      "orbs": 0,
      "isMasterClient": false,
      "isDisconnected": false,
      "isDead": false,
      "isSpectating": false,
      "overrideSpeed": null,
      "overrideCameraSize": null,
      "cameraSize": 3,
      "speed": 3,
      "joinedAt": 1627524400,
      "hash": "ASQXKvdbM",
      "lastReportedTime": "1627524402054",
      "lastUpdate": 1627524403,
      "gameMode": "Sprite Leader",
      "log": {
        "kills": [],
        "deaths": [],
        "revenge": 0,
        "resetPosition": 0
      }
    }
  ],
  "connectedPlayers": [
    "Shadowdeath",
    "mrtri1606",
    "aepol",
    "fenears",
    "duolaameng",
    "Guest602",
    "coco",
    "Unknown246"
  ],
  "rewardItemAmount": 0.05,
  "rewardWinnerAmount": 0.2,
  "totalLegitPlayers": 7,
  "gameMode": "Sprite Leader",
  "orbs": []
}