{
  "version": "0.14.0",
  "round": {
    "index": 15,
    "startedAt": 1627408795
  },
  "clientTotal": 4,
  "playerTotal": 2,
  "spectatorTotal": 0,
  "recentPlayersTotal": 3,
  "spritesTotal": 52,
  "leaderboard": [
    {
      "name": "aepol",
      "id": "u0m8b7X79u5zqjQ_AAKL",
      "avatar": 1,
      "network": "bsc",
      "address": "0xDcc850Ed895626561DaEdf6c6Dc9f8D29a67D94C",
      "device": "desktop",
      "position": {
        "x": -0.1869799062264107,
        "y": -11.005267330527513
      },
      "target": {
        "x": -0.91,
        "y": -10.31
      },
      "clientPosition": {
        "x": -0.2,
        "y": -11.01
      },
      "rotation": null,
      "xp": 86.89999999999945,
      "latency": 40.5,
      "kills": 1,
      "deaths": 0,
      "points": 219,
      "evolves": 18,
      "powerups": 132,
      "rewards": 4,
      "orbs": 1,
      "isMasterClient": false,
      "isDisconnected": false,
      "isDead": false,
      "isSpectating": false,
      "overrideSpeed": null,
      "overrideCameraSize": null,
      "cameraSize": 2,
      "speed": 1.5,
      "joinedAt": 1627408756,
      "hash": "+M7q7BvqU",
      "lastReportedTime": "1627408908019",
      "lastUpdate": 1627408907,
      "gameMode": "Marco Polo",
      "log": {
        "kills": [
          "IGCOrfQfI"
        ],
        "deaths": [],
        "revenge": 0,
        "resetPosition": 0
      },
      "startedRoundAt": 1627408795
    },
    {
      "name": "Hoangdaooo",
      "id": "PbLp-f2gM-g8U5UAAAKP",
      "avatar": 2,
      "network": "bsc",
      "address": "0xfb157F7Ae07ffE0e75CbdCd247590E5961A16c64",
      "device": "desktop",
      "position": {
        "x": -7.139793985226518,
        "y": -6.270771911013272
      },
      "target": {
        "x": -10.72,
        "y": -6.04
      },
      "clientPosition": {
        "x": -6.91,
        "y": -6.21
      },
      "rotation": null,
      "xp": 32.45599999999954,
      "latency": 40.5,
      "kills": 1,
      "deaths": 1,
      "points": 190,
      "evolves": 24,
      "powerups": 152,
      "rewards": 4,
      "orbs": 0,
      "isMasterClient": false,
      "isDisconnected": false,
      "isDead": false,
      "isSpectating": false,
      "overrideSpeed": null,
      "overrideCameraSize": null,
      "cameraSize": 2,
      "speed": 1.5,
      "joinedAt": 1627408883,
      "hash": "IGCOrfQfI",
      "lastReportedTime": "1627408907978",
      "lastUpdate": 1627408908,
      "gameMode": "Marco Polo",
      "log": {
        "kills": [
          "fJV6+OL+M"
        ],
        "deaths": [
          "+M7q7BvqU"
        ],
        "revenge": 0,
        "resetPosition": 0
      }
    },
    {
      "name": "Warpat",
      "id": "fMsCr-VSSzgeX5CtAAKH",
      "avatar": 1,
      "network": "bsc",
      "address": "0x20a67C9c00aA3B3b99D32D01d8Ec0719c7E522AF",
      "device": "desktop",
      "position": {
        "x": -2.7446423756099088,
        "y": -7.589230358208181
      },
      "target": {
        "x": -2.08,
        "y": -6.91
      },
      "clientPosition": {
        "x": -2.78,
        "y": -7.62
      },
      "rotation": null,
      "xp": 47.9039999999996,
      "latency": 0,
      "kills": 0,
      "deaths": 1,
      "points": 24,
      "evolves": 4,
      "powerups": 29,
      "rewards": 0,
      "orbs": 0,
      "isMasterClient": false,
      "isDisconnected": true,
      "isDead": true,
      "isSpectating": false,
      "overrideSpeed": null,
      "overrideCameraSize": null,
      "cameraSize": 2,
      "speed": 1.5,
      "joinedAt": null,
      "hash": "fJV6+OL+M",
      "lastReportedTime": "1627408821210",
      "lastUpdate": 1627408821,
      "gameMode": "Marco Polo",
      "log": {
        "kills": [],
        "deaths": [
          "IGCOrfQfI"
        ],
        "revenge": 0,
        "resetPosition": 0
      },
      "startedRoundAt": 1627408795
    }
  ],
  "connectedPlayers": [
    "Unknown967",
    "Unknown22",
    "aepol",
    "Hoangdaooo"
  ],
  "rewardItemAmount": 0.04,
  "rewardWinnerAmount": 0.16,
  "totalLegitPlayers": 4,
  "gameMode": "Marco Polo",
  "orbs": [
    {
      "id": "YWjZCTRAA8",
      "type": 4,
      "points": 45,
      "scale": 45,
      "position": {
        "x": -12.794134160952213,
        "y": -10.178692337625384
      }
    }
  ],
  "currentReward": {
    "type": "rune",
    "symbol": "thul",
    "quantity": 98.74000000000001,
    "id": "JgaGU_yAsu",
    "position": {
      "x": -16.32,
      "y": -15.7774
    }
  }
}